{
    "status": "Fix Released", 
    "last_updated": "2016-07-14 13:02:33.558446+00:00", 
    "description": "https://review.openstack.org/145004\nDear bug triager. This bug was created since a commit was marked with DOCIMPACT.\nYour project \"openstack/nova\" is set up so that we directly report the documentation bugs against it. If this needs changing, the docimpact-group option needs to be added for the project. You can ask the OpenStack infra team (#openstack-infra on freenode) for help if you need to.\n\ncommit e215e6cba9922e98cb358891a3f9be2e809d770f\nAuthor: Lucian Petrut <email address hidden>\nDate:   Mon Jan 5 16:38:10 2015 +0200\n\n    HyperV: Nova serial console access support\n    \n    Hyper-V provides a solid interface for accessing serial ports via\n    named pipes, already employed in the Nova serial console log\n    implementation.\n    \n    This patch makes use of this interface by implementing a simple TCP\n    socket proxy, providing access to instance serial console ports.\n    \n    DocImpact\n    \n    Implements: blueprint hyperv-serial-ports\n    \n    Change-Id: I58c328391a80ee8b81f66b2e09a1bfa4b26e584c\n", 
    "tags": [
        "doc", 
        "hyper-v", 
        "low-hanging-fruit", 
        "nova"
    ], 
    "importance": "Low", 
    "heat": 6, 
    "link": "https://bugs.launchpad.net/nova/+bug/1584199", 
    "owner": "https://api.launchpad.net/1.0/~yohoffman", 
    "id": 1584199, 
    "index": 2009, 
    "openned": "2016-05-20 19:59:02.301865+00:00", 
    "created": "2016-05-20 19:59:02.301865+00:00", 
    "title": "    HyperV: Nova serial console access support", 
    "comments": [
        {
            "content": "https://review.openstack.org/145004\nDear bug triager. This bug was created since a commit was marked with DOCIMPACT.\nYour project \"openstack/nova\" is set up so that we directly report the documentation bugs against it. If this needs changing, the docimpact-group option needs to be added for the project. You can ask the OpenStack infra team (#openstack-infra on freenode) for help if you need to.\n\ncommit e215e6cba9922e98cb358891a3f9be2e809d770f\nAuthor: Lucian Petrut <email address hidden>\nDate:   Mon Jan 5 16:38:10 2015 +0200\n\n    HyperV: Nova serial console access support\n    \n    Hyper-V provides a solid interface for accessing serial ports via\n    named pipes, already employed in the Nova serial console log\n    implementation.\n    \n    This patch makes use of this interface by implementing a simple TCP\n    socket proxy, providing access to instance serial console ports.\n    \n    DocImpact\n    \n    Implements: blueprint hyperv-serial-ports\n    \n    Change-Id: I58c328391a80ee8b81f66b2e09a1bfa4b26e584c\n", 
            "date_created": "2016-05-20 19:59:02.301865+00:00", 
            "author": "https://api.launchpad.net/1.0/~hudson-openstack"
        }, 
        {
            "content": "It's a simple update of the support-matrix at [1].\n\nReferences:\n[1] https://github.com/openstack/nova/blob/3f96f3039a17e2cad15c05c4fe2d61ee16a14a80/doc/source/support-matrix.ini#L808-L810", 
            "date_created": "2016-05-24 12:10:51.396549+00:00", 
            "author": "https://api.launchpad.net/1.0/~mzoeller"
        }, 
        {
            "content": "Fix proposed to branch: master\nReview: https://review.openstack.org/320477", 
            "date_created": "2016-05-24 14:16:31.088037+00:00", 
            "author": "https://api.launchpad.net/1.0/~hudson-openstack"
        }, 
        {
            "content": "Reviewed:  https://review.openstack.org/320477\nCommitted: https://git.openstack.org/cgit/openstack/nova/commit/?id=74d6c42a1ff9b73ee4b28bf131b274607360fd49\nSubmitter: Jenkins\nBranch:    master\n\ncommit 74d6c42a1ff9b73ee4b28bf131b274607360fd49\nAuthor: Yosef Hoffman <email address hidden>\nDate:   Mon May 23 21:49:20 2016 -0400\n\n    Update Support Matrix\n    \n    HyperV: Nova serial console access support [1] has been merged\n    successfully. Update support matrix accordingly.\n    \n    [1] https://review.openstack.org/145004\n    \n    Change-Id: Ie6792e91c5c6c24d4af448605e4bb7d245bf41a8\n    Closes-Bug: #1584199\n", 
            "date_created": "2016-06-09 10:25:22.585700+00:00", 
            "author": "https://api.launchpad.net/1.0/~hudson-openstack"
        }, 
        {
            "content": "This issue was fixed in the openstack/nova 14.0.0.0b2 development milestone.", 
            "date_created": "2016-07-14 13:02:32.465004+00:00", 
            "author": "https://api.launchpad.net/1.0/~doug-hellmann"
        }
    ], 
    "closed": "2016-06-09 10:25:19.759347+00:00"
}