{
    "status": "Invalid", 
    "last_updated": "2016-10-12 11:48:31.598799+00:00", 
    "description": "1\u3001Version\nroot@controller:~# dpkg -l | grep nova\nii  nova-api                            1:2015.1.0-0ubuntu1~cloud0            all          OpenStack Compute - API frontend\nii  nova-cert                           1:2015.1.0-0ubuntu1~cloud0            all          OpenStack Compute - certificate management\nii  nova-common                         1:2015.1.0-0ubuntu1~cloud0            all          OpenStack Compute - common files\nii  nova-conductor                      1:2015.1.0-0ubuntu1~cloud0            all          OpenStack Compute - conductor service\nii  nova-consoleauth                    1:2015.1.0-0ubuntu1~cloud0            all          OpenStack Compute - Console Authenticator\nii  nova-novncproxy                     1:2015.1.0-0ubuntu1~cloud0            all          OpenStack Compute - NoVNC proxy\nii  nova-scheduler                      1:2015.1.0-0ubuntu1~cloud0            all          OpenStack Compute - virtual machine scheduler\nii  python-nova                         1:2015.1.0-0ubuntu1~cloud0            all          OpenStack Compute Python libraries\nii  python-novaclient                   1:2.22.0-0ubuntu1~cloud0              all          client library for OpenStack Compute API\n\nvms / glance / volume backend storage all use ceph rbd\n\n\n2\u3001Reproduce steps:\na) Boot an instance\nb) attach an volume to the instance\nc) shut off the instance\nd) start the instance and detach the volume quickly until return success\ne) login the instance find the  volume of vdb is still exsit and can be used.\nf) show the volume status have been from in-used to avaiable", 
    "tags": [
        "ceph", 
        "libvirt"
    ], 
    "importance": "High", 
    "heat": 6, 
    "link": "https://bugs.launchpad.net/nova/+bug/1485399", 
    "owner": "None", 
    "id": 1485399, 
    "index": 1795, 
    "openned": "2015-08-17 01:29:17.221719+00:00", 
    "created": "2015-08-17 01:29:17.221719+00:00", 
    "title": "detach volume just then starting instance success but not in the instance\uff0c rbd backend", 
    "comments": [
        {
            "content": "1\u3001Version\nroot@controller:~# dpkg -l | grep nova\nii  nova-api                            1:2015.1.0-0ubuntu1~cloud0            all          OpenStack Compute - API frontend\nii  nova-cert                           1:2015.1.0-0ubuntu1~cloud0            all          OpenStack Compute - certificate management\nii  nova-common                         1:2015.1.0-0ubuntu1~cloud0            all          OpenStack Compute - common files\nii  nova-conductor                      1:2015.1.0-0ubuntu1~cloud0            all          OpenStack Compute - conductor service\nii  nova-consoleauth                    1:2015.1.0-0ubuntu1~cloud0            all          OpenStack Compute - Console Authenticator\nii  nova-novncproxy                     1:2015.1.0-0ubuntu1~cloud0            all          OpenStack Compute - NoVNC proxy\nii  nova-scheduler                      1:2015.1.0-0ubuntu1~cloud0            all          OpenStack Compute - virtual machine scheduler\nii  python-nova                         1:2015.1.0-0ubuntu1~cloud0            all          OpenStack Compute Python libraries\nii  python-novaclient                   1:2.22.0-0ubuntu1~cloud0              all          client library for OpenStack Compute API\n\nvms / glance / volume backend storage all use ceph rbd\n\n\n2\u3001Reproduce steps:\na) Boot an instance\nb) attach an volume to the instance\nc) shut off the instance\nd) start the instance and detach the volume quickly until return success\ne) login the instance find the  volume of vdb is still exsit and can be used.\nf) show the volume status have been from in-used to avaiable", 
            "date_created": "2015-08-17 01:29:17.221719+00:00", 
            "author": "https://api.launchpad.net/1.0/~fengyueqiao"
        }, 
        {
            "content": "Currently working on triaging this, trying to reproduce.", 
            "date_created": "2016-02-03 21:52:38.284108+00:00", 
            "author": "https://api.launchpad.net/1.0/~auggy"
        }, 
        {
            "content": "I just verified this without Ceph to make sure there was no issue with attaching and detaching volumes generally and was unable to reproduce.\n\nTo clarify, the problem being reported looks like if you detach a Ceph volume while an instance is booting up, the instance doesn't register it as detached.\n\nMarking as Confirmed to get into the triage queue so someone with Ceph can attempt to reproduce this.", 
            "date_created": "2016-02-05 03:12:13.862461+00:00", 
            "author": "https://api.launchpad.net/1.0/~auggy"
        }, 
        {
            "content": "You phenomenon just look like my bug report\nhttps://bugs.launchpad.net/nova/+bug/1631692\nMaybe the two reasons are the same.", 
            "date_created": "2016-10-10 10:14:42.941939+00:00", 
            "author": "https://api.launchpad.net/1.0/~tanyy1990"
        }, 
        {
            "content": "I tried reproducing this \n\nHere are my observations\n\n[stack@controller devstack]$ nova suspend test\n[stack@controller devstack]$ nova list\n+--------------------------------------+------+-----------+------------+-------------+-------------------------------------------------------+\n| ID                                   | Name | Status    | Task State | Power State | Networks                                              |\n+--------------------------------------+------+-----------+------------+-------------+-------------------------------------------------------+\n| a3e5e950-a51f-483a-ac48-85203bdb0bc9 | test | SUSPENDED | -          | Shutdown    | private=10.0.0.3, 2001:db8:8000:0:f816:3eff:fe0b:f50c |\n+--------------------------------------+------+-----------+------------+-------------+-------------------------------------------------------+\n[stack@controller devstack]$ nova resume test && nova volume-detach a3e5e950-a51f-483a-ac48-85203bdb0bc9 29dd9434-7559-404b-9c61-9d943936c2bf\nERROR (Conflict): Cannot 'detach_volume' instance a3e5e950-a51f-483a-ac48-85203bdb0bc9 while it is in vm_state suspended (HTTP 409) (Request-ID: req-8049116f-3e4c-476e-a475-9e67c874e65f)\n\n\nAs you can see that in this case the detach_volume did not go through because of the state suspended.", 
            "date_created": "2016-10-12 10:47:29.523217+00:00", 
            "author": "https://api.launchpad.net/1.0/~parora"
        }, 
        {
            "content": "I tried the above with another command\n\nnova resume test & nova volume-detach a3e5e950-a51f-483a-ac48-85203bdb0bc9 29dd9434-7559-404b-9c61-9d943936c2bf \n\nPlease confirm if you are able to still see this issue.", 
            "date_created": "2016-10-12 11:48:30.820553+00:00", 
            "author": "https://api.launchpad.net/1.0/~parora"
        }
    ], 
    "closed": "2016-10-12 10:47:09.553067+00:00"
}