{
    "status": "Fix Released", 
    "last_updated": "2013-10-17 11:56:06.349397+00:00", 
    "description": "At this commit level on master:\n\nhttps://github.com/openstack/nova/commit/4a4988a0a8ea7971ea80a1d9e96f0becc6958dda\n\nUsing the powervm driver, this is the scenario:\n\n1. Boot an instance, setup networking, etc, everything is fine, the instance vm_state is ACTIVE and power_state is 1 (running).\n2. From the backing IVM hypervisor, stop the instance.\n3. Wait 15 minutes (the default sync power state task is 10 minute intervals, this hasn't been changed in the config).\n4. Check the instance status, the vm_state is still ACTIVE but should be SHUTDOWN because the _sync_power_state method in the compute manager should clean it up based on the state of the instance in the hypervisor.\n\nThere is a stack trace in the logs from when the sync_power_state task is running:\n\nhttp://paste.openstack.org/show/39361/", 
    "tags": [
        "unified-objects"
    ], 
    "importance": "High", 
    "heat": 26, 
    "link": "https://bugs.launchpad.net/nova/+bug/1195849", 
    "owner": "https://api.launchpad.net/1.0/~mriedem", 
    "id": 1195849, 
    "index": 1144, 
    "openned": "2013-06-28 18:38:43.626201+00:00", 
    "created": "2013-06-28 18:38:43.626201+00:00", 
    "title": "_sync_power_state fails when instance is powered off", 
    "comments": [
        {
            "content": "At this commit level on master:\n\nhttps://github.com/openstack/nova/commit/4a4988a0a8ea7971ea80a1d9e96f0becc6958dda\n\nUsing the powervm driver, this is the scenario:\n\n1. Boot an instance, setup networking, etc, everything is fine, the instance vm_state is ACTIVE and power_state is 1 (running).\n2. From the backing IVM hypervisor, stop the instance.\n3. Wait 15 minutes (the default sync power state task is 10 minute intervals, this hasn't been changed in the config).\n4. Check the instance status, the vm_state is still ACTIVE but should be SHUTDOWN because the _sync_power_state method in the compute manager should clean it up based on the state of the instance in the hypervisor.\n\nThere is a stack trace in the logs from when the sync_power_state task is running:\n\nhttp://paste.openstack.org/show/39361/\n\nThere is no error message initially. I had to change the code as shown below to bring out the error message. There are no other changes.\n\ndiff /usr/lib/python2.6/site-packages/nova/compute/manager.py /usr/lib/python2.6/site-packages/nova/compute/manager.py.orig\n4002,4009c4002,4004\n<             try:\n<                 db_instance.power_state = vm_power_state\n<                 db_instance.save()                 #  <--------------------------------- this statement fails\n<                 db_power_state = vm_power_state\n<             except Exception:\n<                 LOG.exception(_(\"error during db_instance.save()\"\n<                                 \" in _sync_instance_power_state.\"),\n<                               instance=db_instance)\n---\n>             db_instance.power_state = vm_power_state\n>             db_instance.save()\n>             db_power_state = vm_power_state\n\nSo the line numbers in the paste bin will be a little off.", 
            "date_created": "2013-06-28 18:38:43.626201+00:00", 
            "author": "https://api.launchpad.net/1.0/~mriedem"
        }, 
        {
            "content": "Talked with Dan Smith about this on IRC, looks like the conductor.rpcapi.compute_stop method was missed in this review:\n\nhttps://review.openstack.org/#/c/30192/\n\nSo the fix is to just do the same in conductor.rpcapi.compute_stop as in compute.rpcapi.stop_instance here:\n\nhttps://review.openstack.org/#/c/30192/26/nova/compute/rpcapi.py", 
            "date_created": "2013-06-28 19:06:06.872349+00:00", 
            "author": "https://api.launchpad.net/1.0/~mriedem"
        }, 
        {
            "content": "Fix proposed to branch: master\nReview: https://review.openstack.org/34947", 
            "date_created": "2013-06-28 20:11:02.618138+00:00", 
            "author": "https://api.launchpad.net/1.0/~hudson-openstack"
        }, 
        {
            "content": "Reviewed:  https://review.openstack.org/34947\nCommitted: http://github.com/openstack/nova/commit/190d8ca4524df0b0fdd3514886672f51bd7da43a\nSubmitter: Jenkins\nBranch:    master\n\ncommit 190d8ca4524df0b0fdd3514886672f51bd7da43a\nAuthor: Matt Riedemann <email address hidden>\nDate:   Thu Jul 18 14:23:15 2013 -0700\n\n    Handle instance objects in conductor compute_stop\n    \n    The compute manager is sending instance objects to\n    compute_stop in conductor but conductor's compute_stop\n    RPC proxy wasn't handling objects. This patch fixes that\n    and also handles compatibility with older installations\n    using the dict-style format in the conductor compute_stop\n    RPC proxy.\n    \n    Fixes bug 1195849\n    \n    Change-Id: Ib678df424a58a0d7023ce3b2bdd5001998daf398\n", 
            "date_created": "2013-07-20 00:55:27.986774+00:00", 
            "author": "https://api.launchpad.net/1.0/~hudson-openstack"
        }
    ], 
    "closed": "2013-09-05 15:38:42.066060+00:00"
}