{
    "status": "Fix Released", 
    "last_updated": "2011-09-22 13:40:03.688458+00:00", 
    "description": "We need to ensure all of our bases are covered for XenAPI Unrescue.", 
    "tags": [], 
    "importance": "Wishlist", 
    "heat": 6, 
    "link": "https://bugs.launchpad.net/nova/+bug/741903", 
    "owner": "None", 
    "id": 741903, 
    "index": 2294, 
    "openned": "2011-03-24 17:13:24.773666+00:00", 
    "created": "2011-03-24 17:13:24.773666+00:00", 
    "title": "More thorough XenAPI Unrescue test coverage", 
    "comments": [
        {
            "content": "We need to ensure all of our bases are covered for XenAPI Unrescue.", 
            "date_created": "2011-03-24 17:13:24.773666+00:00", 
            "author": "https://api.launchpad.net/1.0/~jk0"
        }, 
        {
            "content": "Done in a previous branch.", 
            "date_created": "2011-07-28 17:15:03.274917+00:00", 
            "author": "https://api.launchpad.net/1.0/~jk0"
        }
    ], 
    "closed": "2011-09-22 13:40:02.008886+00:00"
}