{
    "status": "Fix Released", 
    "last_updated": "2011-04-15 08:34:12.605657+00:00", 
    "description": "Glance trunk has just replaced image `type` with `disk_format` and `container_format`. In order to keep both trunks working together, we need to fix Nova to use the new-style ASAP.", 
    "tags": [], 
    "importance": "High", 
    "heat": 6, 
    "link": "https://bugs.launchpad.net/nova/+bug/731470", 
    "owner": "https://api.launchpad.net/1.0/~rconradharris", 
    "id": 731470, 
    "index": 366, 
    "created": "2011-03-08 17:29:54.554660+00:00", 
    "title": "Nova should use disk_format and container_format", 
    "comments": [
        {
            "content": "Glance trunk has just replaced image `type` with `disk_format` and `container_format`. In order to keep both trunks working together, we need to fix Nova to use the new-style ASAP.", 
            "date_created": "2011-03-08 17:29:54.554660+00:00", 
            "author": "https://api.launchpad.net/1.0/~rconradharris"
        }
    ]
}