{
    "status": "Fix Released", 
    "last_updated": "2016-01-21 13:44:14.066565+00:00", 
    "description": "Hi! I'm spell checking the nova .\nIn nova/network/manager.py\n\nDetail is as followed\n\n  # NOTE(vish): I strongy suspect the v6 subnet is not used\n  #             anywhere, but support it just in case\n  # add the v6 address to the v6 subnet\n\nThe correct should be\n  # NOTE(vish): I strongly suspect the v6 subnet is not used\n  #             anywhere, but support it just in case\n  # add the v6 address to the v6 subnet\n\n\"strongy\" is incorrect", 
    "tags": [
        "low-hanging-fruit"
    ], 
    "importance": "Low", 
    "heat": 6, 
    "link": "https://bugs.launchpad.net/nova/+bug/1492120", 
    "owner": "https://api.launchpad.net/1.0/~zhang-quanwei", 
    "id": 1492120, 
    "index": 571, 
    "created": "2015-09-04 06:23:56.911154+00:00", 
    "title": "spelling mistake  in comment in nova/network/manager.py", 
    "comments": [
        {
            "content": "Hi! I'm spell checking the nova .\nIn nova/network/manager.py\n\nDetail is as followed\n\n  # NOTE(vish): I strongy suspect the v6 subnet is not used\n  #             anywhere, but support it just in case\n  # add the v6 address to the v6 subnet\n\nThe correct should be\n  # NOTE(vish): I strongly suspect the v6 subnet is not used\n  #             anywhere, but support it just in case\n  # add the v6 address to the v6 subnet\n\n\"strongy\" is incorrect", 
            "date_created": "2015-09-04 06:23:56.911154+00:00", 
            "author": "https://api.launchpad.net/1.0/~zhang-quanwei"
        }, 
        {
            "content": "parts, venkatamahesh, \n\nEither one of you logged a review yet?\n\n-- Dims", 
            "date_created": "2015-09-05 01:22:41.643031+00:00", 
            "author": "https://api.launchpad.net/1.0/~dims-v"
        }, 
        {
            "content": "I will fix it", 
            "date_created": "2015-09-05 05:54:40.131786+00:00", 
            "author": "https://api.launchpad.net/1.0/~zhang-quanwei"
        }, 
        {
            "content": "Fix proposed to branch: master\nReview: https://review.openstack.org/220877", 
            "date_created": "2015-09-07 04:23:23.733173+00:00", 
            "author": "https://api.launchpad.net/1.0/~hudson-openstack"
        }, 
        {
            "content": "Reviewed:  https://review.openstack.org/220877\nCommitted: https://git.openstack.org/cgit/openstack/nova/commit/?id=de3cc5eda5ce794e913b5b09652ca3be110a7946\nSubmitter: Jenkins\nBranch:    master\n\ncommit de3cc5eda5ce794e913b5b09652ca3be110a7946\nAuthor: partys <email address hidden>\nDate:   Mon Sep 7 03:50:17 2015 +0000\n\n     Rectify spelling mistake in nova\n    \n     Change 'strongy' to 'strongly' in file  /nova/network/manager.py\n    \n     Closes-Bug: #1492120\n    \n    Change-Id: Ifb184f4b03c646ef104272aa42411d248e7400c3\n", 
            "date_created": "2015-12-17 17:59:20.380635+00:00", 
            "author": "https://api.launchpad.net/1.0/~hudson-openstack"
        }, 
        {
            "content": "This issue was fixed in the openstack/nova 13.0.0.0b2 development milestone.", 
            "date_created": "2016-01-21 13:44:13.295791+00:00", 
            "author": "https://api.launchpad.net/1.0/~ttx"
        }
    ]
}